BlockchainDataBase/Block.py
BlockchainDataBase/Blockchain.py
BlockchainDataBase/__init__.py
BlockchainDataBase/Data/DBManage.py
BlockchainDataBase/Data/__init__.py
BlockchainDataBase-1.1.4.dist-info/METADATA
BlockchainDataBase-1.1.4.dist-info/RECORD
BlockchainDataBase-1.1.4.dist-info/WHEEL
BlockchainDataBase-1.1.4.dist-info/top_level.txt
