Metadata-Version: 2.1
Name: BlockchainDataBase
Version: 1.1.4
Summary: A Simple Blockchain Database.
Home-page: https://github.com/DEMG-DEV/SimpleBlockchainDataBase
Author: David Mendez Guardado
Author-email: demg@outlook.com
License: UNKNOWN
Platform: UNKNOWN
Classifier: Programming Language :: Python :: 3
Classifier: License :: OSI Approved :: MIT License
Classifier: Operating System :: OS Independent
